{
  "schemaVersion": 1,
  "moduleSetVersion": "20260723.07",
  "entryMinVersion": 4,
  "sourceRef": "agent/initialize-project-skeleton",
  "modules": [
    {
      "name": "ch_01_base.js",
      "path": "src/ch_01_base.js",
      "sha": "563791ff518078bfd57d7b73fc51b9c7482a3ffb"
    },
    {
      "name": "ch_02_log.js",
      "path": "src/ch_02_log.js",
      "sha": "581d7a9a0e47bdee2be0341cbfbe6b0308c207bb"
    },
    {
      "name": "ch_03_database.js",
      "path": "src/ch_03_database.js",
      "sha": "3c3ea319844cf9470aff385def30cac11bf95e3c"
    },
    {
      "name": "ch_04_clipboard.js",
      "path": "src/ch_04_clipboard.js",
      "sha": "9dbb0aa8e3bc7318ab6ddfc39fa9c67c8ed739ae"
    },
    {
      "name": "ch_05_classifier.js",
      "path": "src/ch_05_classifier.js",
      "sha": "7f4ea64a79b38eceab0351a6129c0901366aa404"
    },
    {
      "name": "ch_06_repository.js",
      "path": "src/ch_06_repository.js",
      "sha": "8442c2eb741ea21e3f713b8470655ee83e57235f"
    },
    {
      "name": "ch_07_theme.js",
      "path": "src/ch_07_theme.js",
      "sha": "bcdb99700fffbb54d6315b773e051aa78294de1b"
    },
    {
      "name": "ch_08_window.js",
      "path": "src/ch_08_window.js",
      "sha": "abc37b0a008ccaecac0a0d4a46ef7c76ee40f1db"
    },
    {
      "name": "ch_09_list.js",
      "path": "src/ch_09_list.js",
      "sha": "8060dd75f23147e3fbc2c231f8138e7051cd159f"
    },
    {
      "name": "ch_10_editor.js",
      "path": "src/ch_10_editor.js",
      "sha": "9cfccb00161202ba5a798a30c799168579634c61"
    },
    {
      "name": "ch_11_filter.js",
      "path": "src/ch_11_filter.js",
      "sha": "00071ce7b23f504c69fdd621b668892671b413c5"
    },
    {
      "name": "ch_12_translation.js",
      "path": "src/ch_12_translation.js",
      "sha": "6e379d8a7cb5363ed56ba1f6af05b844c10d40e5"
    },
    {
      "name": "ch_13_settings.js",
      "path": "src/ch_13_settings.js",
      "sha": "47a1b31a27fcff454cb9d3a243805c05f596dd00"
    },
    {
      "name": "ch_14_event_bus.js",
      "path": "src/ch_14_event_bus.js",
      "sha": "1340517a82be26bb0bbf71454c246067344ce019"
    },
    {
      "name": "ch_15_app.js",
      "path": "src/ch_15_app.js",
      "sha": "1c9a02037e75ac3fc5b3c0c0e3930daa9aa1d740"
    }
  ]
}
